line_api/__init__.py
line_api/core/__init__.py
line_api/core/config.py
line_api/core/exceptions.py
line_api/flex_messages/__init__.py
line_api/flex_messages/builders.py
line_api/flex_messages/models.py
line_api/flex_messages/utils.py
line_api/messaging/__init__.py
line_api/messaging/client.py
line_api/messaging/models.py
line_api/tests/test_webhook.py
line_api/webhook/__init__.py
line_api/webhook/handler.py
line_api/webhook/models.py
line_api/webhook/signature.py
line_api/py.typed
line_api_integration-1.0.0.dist-info/METADATA
line_api_integration-1.0.0.dist-info/WHEEL
line_api_integration-1.0.0.dist-info/licenses/LICENSE
line_api_integration-1.0.0.dist-info/RECORD
