Metadata-Version: 2.4
Name: line-api-integration
Version: 1.0.0
Summary: Comprehensive LINE API integration library with Flex Messages, Rich Menus, LINE Login, LIFF, and Mini Apps
Project-URL: Homepage, https://github.com/lumduan/line-api
Project-URL: Documentation, https://github.com/lumduan/line-api/blob/main/README.md
Project-URL: Changelog, https://github.com/lumduan/line-api/blob/main/CHANGELOG.md
Project-URL: Issues, https://github.com/lumduan/line-api/issues
Project-URL: Repository, https://github.com/lumduan/line-api
Author-email: LINE API Integration Library <b@candythink.com>
License: MIT License
License-File: LICENSE
Keywords: api,bot,flex-message,liff,line,messaging,mini-app,rich-menu
Classifier: Development Status :: 5 - Production/Stable
Classifier: Intended Audience :: Developers
Classifier: License :: OSI Approved :: MIT License
Classifier: Programming Language :: Python :: 3
Classifier: Programming Language :: Python :: 3.9
Classifier: Programming Language :: Python :: 3.10
Classifier: Programming Language :: Python :: 3.11
Classifier: Programming Language :: Python :: 3.12
Classifier: Programming Language :: Python :: 3.13
Classifier: Topic :: Communications :: Chat
Classifier: Topic :: Internet :: WWW/HTTP :: Dynamic Content
Classifier: Topic :: Software Development :: Libraries :: Python Modules
Classifier: Typing :: Typed
Requires-Python: >=3.9
Requires-Dist: fastapi>=0.115.14
Requires-Dist: httpx>=0.26.0
Requires-Dist: pydantic-settings>=2.10.1
Requires-Dist: pydantic>=2.5.0
Requires-Dist: pyperclip>=1.9.0
Requires-Dist: python-dotenv>=1.0.0
Requires-Dist: uvicorn[standard]>=0.35.0
Provides-Extra: dev
Requires-Dist: ipython>=8.0.0; extra == 'dev'
Requires-Dist: mypy>=1.7.0; extra == 'dev'
Requires-Dist: pytest-asyncio>=0.23.0; extra == 'dev'
Requires-Dist: pytest-cov>=4.1.0; extra == 'dev'
Requires-Dist: pytest-mock>=3.12.0; extra == 'dev'
Requires-Dist: pytest>=7.4.0; extra == 'dev'
Requires-Dist: rich>=13.7.0; extra == 'dev'
Requires-Dist: ruff>=0.1.6; extra == 'dev'
Requires-Dist: types-requests>=2.31.0; extra == 'dev'
